[
    {
        "id": "4c047528ca19e9948f31c76f077c365e1125e788",
        "filename": "4c047528ca19e9948f31c76f077c365e1125e788.jpeg",
        "name": "Foggy Intersection",
        "difficulty": 4,
        "hint": "Somewhere with water.",
        "coordinates": {
            "lat": 49.277692226882145,
            "lng": -122.90898263454439
        },
        "keywords": ["fog", "intersection"]
    },
    {
        "id": "5c293856f6b7264268e9c1437c9e30a6c78f6c87",
        "filename": "5c293856f6b7264268e9c1437c9e30a6c78f6c87.jpeg",
        "name": "Foggy Fish Pond",
        "difficulty": 2,
        "hint": "If the sun is in the picture, what direction and hence what side must the picture be taken from.",
        "coordinates": { "lat": 49.2789346088565, "lng": -122.91710972785951 },
        "keywords": ["fog", "fish-pond", "sun", "water"]
    },
    {
        "id": "57bc9c5058a29f4200e8d3393b9abcb880bbc7c3",
        "filename": "57bc9c5058a29f4200e8d3393b9abcb880bbc7c3.jpeg",
        "name": "Dark Snowy Road",
        "difficulty": 3,
        "hint": "Lots of buses go near here.",
        "coordinates": {
            "lat": 49.279312566741346,
            "lng": -122.91204035282136
        },
        "keywords": ["snow", "road", "dark"]
    },
    {
        "id": "af3f6d7f9e057ee5776d621d377ecd80f4a7fc2e",
        "filename": "af3f6d7f9e057ee5776d621d377ecd80f4a7fc2e.jpeg",
        "name": "Dark SUB",
        "difficulty": 1,
        "hint": "Near the AQ.",
        "coordinates": {
            "lat": 49.279109589718836,
            "lng": -122.91802167892457
        },
        "keywords": ["dark", "building", "sub"]
    },
    {
        "id": "45763c51aae04cd52d91c7019990422e9bc6214c",
        "filename": "45763c51aae04cd52d91c7019990422e9bc6214c.jpeg",
        "name": "Looking Over Pond Near AQ",
        "difficulty": 3,
        "hint": "Near the AQ.",
        "coordinates": { "lat": 49.27956803663402, "lng": -122.91650354862215 },
        "keywords": ["water", "light"]
    },
    {
        "id": "010394b2d4a955b7583636f5111e852e31854d8b",
        "filename": "010394b2d4a955b7583636f5111e852e31854d8b.jpeg",
        "name": "Bus Loop Foggy",
        "difficulty": 1,
        "hint": "Lots of buses are here.",
        "coordinates": { "lat": 49.27912358816098, "lng": -122.91229248046876 },
        "keywords": ["fog", "bus-loop"]
    },
    {
        "id": "9adc27aee211f9329cb55372befad87f34d3a6d0",
        "filename": "9adc27aee211f9329cb55372befad87f34d3a6d0.jpeg",
        "name": "Rotunda Top",
        "difficulty": 1,
        "hint": "Look at the background.",
        "coordinates": { "lat": 49.27947704750892, "lng": -122.92037129402162 },
        "keywords": ["rotunda", "light"]
    },
    {
        "id": "3bc6566f6bf7b39a3bd2e4221dd79012ba8960d9",
        "filename": "3bc6566f6bf7b39a3bd2e4221dd79012ba8960d9.jpeg",
        "name": "Snowy Bridge",
        "difficulty": 4,
        "hint": "Near some shops.",
        "coordinates": { "lat": 49.27829117270483, "lng": -122.9115498844786 },
        "keywords": ["snow", "bridge"]
    },
    {
        "id": "945e1d76dd89d9f7095e55ceb85efc6741f389f1.jpeg",
        "filename": "945e1d76dd89d9f7095e55ceb85efc6741f389f1.jpeg",
        "name": "Snowy Pond Near AQ",
        "difficulty": 3,
        "hint": "Near the AQ.",
        "coordinates": { "lat": 49.27964852687399, "lng": -122.91641771793367 },
        "keywords": ["water", "ice", "light", "snow"]
    },
    {
        "id": "00eb78fcfb4d2ea6c0d4ab49f945a88333fe1574",
        "filename": "00eb78fcfb4d2ea6c0d4ab49f945a88333fe1574.jpeg",
        "name": "SUB Stairs",
        "difficulty": 3,
        "hint": "In the SUB.",
        "coordinates": {
            "lat": 49.278633640321075,
            "lng": -122.91815578937532
        },
        "keywords": ["light", "stairs", "inside", "sub"]
    },
    {
        "id": "21c41324f2d576ed82ac10d154acdd29302eb16f",
        "filename": "21c41324f2d576ed82ac10d154acdd29302eb16f.jpeg",
        "name": "Rooftop Parking",
        "difficulty": 2,
        "hint": "Around WMC.",
        "coordinates": {
            "lat": 49.279921492796625,
            "lng": -122.92310178279878
        },
        "keywords": ["light", "outside", "parking", "roof"]
    },
    {
        "id": "0c8f7c924cd121c28b76d6e7b089180a0c5066e8",
        "filename": "0c8f7c924cd121c28b76d6e7b089180a0c5066e8.jpeg",
        "name": "Foggy Library View From Rooftop",
        "difficulty": 1,
        "hint": "Facing west.",
        "coordinates": {
            "lat": 49.279652026446676,
            "lng": -122.91722238063812
        },
        "keywords": ["light", "outside", "fog", "roof", "library"]
    },
    {
        "id": "03988cbf87430a3da28f4d743febaf718450a868",
        "filename": "03988cbf87430a3da28f4d743febaf718450a868.jpeg",
        "name": "Bus Loop East View",
        "difficulty": 1,
        "hint": "Lots of buses around here.",
        "coordinates": { "lat": 49.278381665251, "lng": -122.91285574436189 },
        "keywords": ["bus-loop", "light", "outside", "road"]
    },
    {
        "id": "eb10d61af8e06a33d88af08effaecee5b3958422",
        "filename": "eb10d61af8e06a33d88af08effaecee5b3958422.jpeg",
        "name": "South-West AQ",
        "difficulty": 2,
        "hint": "Near the SUB.",
        "coordinates": { "lat": 49.27859864386054, "lng": -122.91754424571992 },
        "keywords": ["inside", "light", "aq", "building"]
    },
    {
        "id": "a4fe5cd09cabe48de35d3c6736dd65857852a110",
        "filename": "a4fe5cd09cabe48de35d3c6736dd65857852a110.jpeg",
        "name": "Periodic Table",
        "difficulty": 3,
        "hint": "In one of the science buildings.",
        "coordinates": { "lat": 49.27797570270808, "lng": -122.91764616966249 },
        "keywords": ["inside", "light", "science"]
    },
    {
        "id": "213a53990b357bf83e88211d159d8badde0a5699",
        "filename": "213a53990b357bf83e88211d159d8badde0a5699.jpeg",
        "name": "Blue Bar Pyramid",
        "difficulty": 4,
        "hint": "It was moved from its previous position.",
        "coordinates": {
            "lat": 49.278056195546846,
            "lng": -122.91803240776063
        },
        "keywords": ["outside", "light", "sculpture"]
    },
    {
        "id": "82999779909ffcce35cfa67ee0355c8ac75886ff",
        "filename": "82999779909ffcce35cfa67ee0355c8ac75886ff.jpeg",
        "name": "Back of the SUB",
        "difficulty": 2,
        "hint": "Around the SUB.",
        "coordinates": { "lat": 49.27818568375093, "lng": -122.91800022125246 },
        "keywords": ["sub", "outside", "light", "stairs"]
    },
    {
        "id": "aecdae2407a09da213ff7375b84429f8757853c1",
        "filename": "aecdae2407a09da213ff7375b84429f8757853c1.jpeg",
        "name": "South-West AQ Stairs",
        "difficulty": 3,
        "hint": "In the AQ.",
        "coordinates": { "lat": 49.27869313424697, "lng": -122.91746377944948 },
        "keywords": ["stairs", "inside", "building", "aq", "light"]
    },
    {
        "id": "85b441fa4446be088f31fa27eba38921903ab971",
        "filename": "85b441fa4446be088f31fa27eba38921903ab971.jpeg",
        "name": "South-West AQ Entrance",
        "difficulty": 2,
        "hint": "Near an entrance to the AQ.",
        "coordinates": { "lat": 49.27876312700912, "lng": -122.91744768619539 },
        "keywords": ["inside", "building", "aq", "light"]
    },
    {
        "id": "58f17ce4480d86a9c4f8402e23c56e74507e75ad",
        "filename": "58f17ce4480d86a9c4f8402e23c56e74507e75ad.jpeg",
        "name": "North Face",
        "difficulty": 2,
        "hint": "Around WMC.",
        "coordinates": {
            "lat": 49.279820005642854,
            "lng": -122.92274773120882
        },
        "keywords": ["outside", "dark", "sculpture"]
    },
    {
        "id": "680a6f7688ff6e5dc22143f9507c558d2c5f969f",
        "filename": "680a6f7688ff6e5dc22143f9507c558d2c5f969f.jpeg",
        "name": "Green Room Under the AQ Stairs",
        "difficulty": 2,
        "hint": "Around the AQ.",
        "coordinates": { "lat": 49.27915858424903, "lng": -122.91756033897401 },
        "keywords": ["green-room", "aq", "inside", "light"]
    },
    {
        "id": "c39772d8c9312611749310bd294056f0c64919dd",
        "filename": "c39772d8c9312611749310bd294056f0c64919dd.jpeg",
        "name": "Back of the SUB Sky View",
        "difficulty": 2,
        "hint": "The building has lots of glass.",
        "coordinates": {
            "lat": 49.278056195546846,
            "lng": -122.91803240776063
        },
        "keywords": ["outside", "light", "sub"]
    },
    {
        "id": "edfb76cc4a6e18652df2ec3c136f84c4dde04af3",
        "filename": "edfb76cc4a6e18652df2ec3c136f84c4dde04af3.jpeg",
        "name": "Hanging Balls",
        "difficulty": 4,
        "hint": "In a science area.",
        "coordinates": { "lat": 49.27797220301647, "lng": -122.91771054267885 },
        "keywords": ["light", "inside", "building"]
    },
    {
        "id": "2f6186e2c3bef28830b14e740d59903870cf18ec",
        "filename": "2f6186e2c3bef28830b14e740d59903870cf18ec.jpeg",
        "name": "Rock Display",
        "difficulty": 5,
        "hint": "In a science wing.",
        "coordinates": { "lat": 49.27812268953193, "lng": -122.9177212715149 },
        "keywords": ["inside", "display", "light", "science"]
    },
    {
        "id": "f880e838cf712109d6c5a89a3d2fea9f20a6f31b",
        "filename": "f880e838cf712109d6c5a89a3d2fea9f20a6f31b.jpeg",
        "name": "Foggy Path",
        "difficulty": 5,
        "hint": "East side of SFU.",
        "coordinates": { "lat": 49.27754523877539, "lng": -122.90822625160219 },
        "keywords": ["outside", "light", "fog", "path"]
    },
    {
        "id": "3fedd25a6a1e10ada88ac3adbfcd360a9373ddf8",
        "filename": "3fedd25a6a1e10ada88ac3adbfcd360a9373ddf8.jpeg",
        "name": "C-9002 and C-9000 Doors",
        "difficulty": 4,
        "hint": "Near the AQ.",
        "coordinates": { "lat": 49.27831517161506, "lng": -122.91761934757234 },
        "keywords": ["room", "inside", "light", "door"]
    },
    {
        "id": "4cf02139d9d25b0abf9b1539d82d8e87ceb3e824",
        "filename": "4cf02139d9d25b0abf9b1539d82d8e87ceb3e824.jpeg",
        "name": "South Side of Green AQ Room",
        "difficulty": 2,
        "hint": "Around the AQ.",
        "coordinates": { "lat": 49.279029098599274, "lng": -122.917375266552 },
        "keywords": ["inside", "light", "aq", "green-room"]
    },
    {
        "id": "2e4d1691540be3fcd6d0cddc3ccf9a74cbd4978b",
        "filename": "2e4d1691540be3fcd6d0cddc3ccf9a74cbd4978b.jpeg",
        "name": "North Mountain View from the AQ",
        "difficulty": 3,
        "hint": "North view from around the middle of SFU. ",
        "coordinates": { "lat": 49.27964852687399, "lng": -122.91704535484314 },
        "keywords": ["outside", "light", "view", "mountains"]
    },
    {
        "id": "385f7ff380ded6a643f8815bb39a222d30b4f39d",
        "filename": "385f7ff380ded6a643f8815bb39a222d30b4f39d.jpeg",
        "name": "South AQ View near the SUB",
        "difficulty": 2,
        "hint": "The glass bridge connects to the SUB.",
        "coordinates": { "lat": 49.2788716155941, "lng": -122.91783928871156 },
        "keywords": ["outside", "light", "aq"]
    },
    {
        "id": "4ece99ea4ade30626f62f4f7b1ac583b84f6ec8c",
        "filename": "4ece99ea4ade30626f62f4f7b1ac583b84f6ec8c.jpeg",
        "name": "Science Road South View",
        "difficulty": 3,
        "hint": "Near parking lots.",
        "coordinates": { "lat": 49.27724426176144, "lng": -122.91302204132081 },
        "keywords": ["road", "outside", "dark"]
    },
    {
        "id": "ad0f1b4c85ba808ca8e40154ae74887a7f421a6e",
        "filename": "ad0f1b4c85ba808ca8e40154ae74887a7f421a6e.jpeg",
        "name": "AQ Fish Pond",
        "difficulty": 1,
        "hint": "In the AQ.",
        "coordinates": {
            "lat": 49.279055345717914,
            "lng": -122.91723847389223
        },
        "keywords": ["fish-pond", "outside", "dark", "aq"]
    },
    {
        "id": "27f53cefc0c52c248ce29e8b849f045324af6ce4",
        "filename": "27f53cefc0c52c248ce29e8b849f045324af6ce4.jpeg",
        "name": "Rolling Green Hills",
        "difficulty": 3,
        "hint": "Near the SUB.",
        "coordinates": { "lat": 49.2781891834274, "lng": -122.9188907146454 },
        "keywords": ["outside", "light", "building"]
    },
    {
        "id": "a6e559ee7170bfa00d40462a0bc94972f0f7504b",
        "filename": "a6e559ee7170bfa00d40462a0bc94972f0f7504b.jpeg",
        "name": "Circular Couches",
        "difficulty": 2,
        "hint": "In the AQ.",
        "coordinates": { "lat": 49.27859864386054, "lng": -122.91750133037569 },
        "keywords": ["inside", "light", "aq"]
    },
    {
        "id": "aad78b0aae687e7e4d27600f21c4f4812a4e3a92",
        "filename": "aad78b0aae687e7e4d27600f21c4f4812a4e3a92.jpeg",
        "name": "SFU Gallery",
        "difficulty": 3,
        "hint": "Looking north.",
        "coordinates": {
            "lat": 49.278341419113644,
            "lng": -122.91648209095003
        },
        "keywords": ["inside", "light", "aq"]
    },
    {
        "id": "ff76eebb1e04f3623c132b676701ecbcf03951b9",
        "filename": "ff76eebb1e04f3623c132b676701ecbcf03951b9.jpeg",
        "name": "AQ South Hallway",
        "difficulty": 2,
        "hint": "A hallway of the AQ.",
        "coordinates": { "lat": 49.27850065363896, "lng": -122.91745305061342 },
        "keywords": ["inside", "light", "aq", "hallway"]
    },
    {
        "id": "5f7609f8014fa5a3af123f04a184aeb380754504",
        "filename": "5f7609f8014fa5a3af123f04a184aeb380754504.jpeg",
        "name": "AQ Mini Ramp",
        "difficulty": 2,
        "hint": "At one of the corners of the AQ.",
        "coordinates": {
            "lat": 49.278248677889465,
            "lng": -122.91613876819612
        },
        "keywords": ["inside", "light", "aq", "ramp"]
    },
    {
        "id": "4cf80b992e03ff5ae5d3970a7f5b2ff122aba06f",
        "filename": "4cf80b992e03ff5ae5d3970a7f5b2ff122aba06f.jpeg",
        "name": "SFU Physics Infinity Mirror",
        "difficulty": 4,
        "hint": "In the SFU physics entrance hallway.",
        "coordinates": { "lat": 49.2779617039401, "lng": -122.91603684425355 },
        "keywords": ["inside", "light", "physics", "attraction"]
    },
    {
        "id": "4356f2ba5f5fad10bdb922dbf4570f8c27314be9",
        "filename": "4356f2ba5f5fad10bdb922dbf4570f8c27314be9.jpeg",
        "name": "AQ Stairs",
        "difficulty": 1,
        "hint": "Goes to the AQ.",
        "coordinates": { "lat": 49.27915508464133, "lng": -122.91801095008852 },
        "keywords": ["outside", "light", "aq", "stairs", "building"]
    },
    {
        "id": "f33893d0bc8100af0e4432f3850c9267b4b747e8",
        "filename": "f33893d0bc8100af0e4432f3850c9267b4b747e8.jpeg",
        "name": "SFU Equatorial Sundial",
        "difficulty": 3,
        "hint": "Neat the observatory.",
        "coordinates": { "lat": 49.27853215051714, "lng": -122.91464209556581 },
        "keywords": ["outside", "light", "attraction"]
    },
    {
        "id": "fe0c54a7d73ecea0b87e7c8cae00fdc0391ffe21",
        "filename": "fe0c54a7d73ecea0b87e7c8cae00fdc0391ffe21.jpeg",
        "name": "SFU Entrance Sign",
        "difficulty": 1,
        "hint": "At a road entrance to SFU.",
        "coordinates": { "lat": 49.273684894300125, "lng": -122.9256981611252 },
        "keywords": ["outside", "light"]
    },
    {
        "id": "26c2d1384c07a7c2ebbbda322a1701805e7d0225",
        "filename": "26c2d1384c07a7c2ebbbda322a1701805e7d0225.jpeg",
        "name": "SFU Physics Floor Solar System",
        "difficulty": 4,
        "hint": "In the SFU physics entrance hallway.",
        "coordinates": { "lat": 49.277891710040635, "lng": -122.9160636663437 },
        "keywords": ["inside", "light", "physics", "attraction"]
    },
    {
        "id": "06aa239bc70ec6e62190d578b2cf8be2ec9bad9b",
        "filename": "06aa239bc70ec6e62190d578b2cf8be2ec9bad9b.jpeg",
        "name": "SFU Physics Chaotic Pendulum",
        "difficulty": 4,
        "hint": "In the SFU physics entrance hallway.",
        "coordinates": { "lat": 49.27797920239947, "lng": -122.91603147983552 },
        "keywords": ["inside", "light", "physics", "attraction"]
    },
    {
        "id": "2e60a5a5a9ff47c9c9553a59a3491b275f37314b",
        "filename": "2e60a5a5a9ff47c9c9553a59a3491b275f37314b.jpeg",
        "name": "SFU Physics Colour Mixing",
        "difficulty": 4,
        "hint": "In the SFU physics entrance hallway.",
        "coordinates": { "lat": 49.27795470455463, "lng": -122.91604220867158 },
        "keywords": ["inside", "light", "physics", "attraction"]
    },
    {
        "id": "f32bdfe1e1c7658808af82f891fb4e6061fd0ec6",
        "filename": "f32bdfe1e1c7658808af82f891fb4e6061fd0ec6.jpeg",
        "name": "Mini SFU Display",
        "difficulty": 3,
        "hint": "In the AQ.",
        "coordinates": {
            "lat": 49.279459549580984,
            "lng": -122.91628360748292
        },
        "keywords": ["inside", "light", "display", "attraction", "aq"]
    },
    {
        "id": "d9dd2f72504d951cd7fa89eb0f139ff5c33d62ee",
        "filename": "d9dd2f72504d951cd7fa89eb0f139ff5c33d62ee.jpeg",
        "name": "SUB Back View",
        "difficulty": 1,
        "hint": "Near the AQ.",
        "coordinates": { "lat": 49.27781471663647, "lng": -122.91809141635896 },
        "keywords": ["outside", "dark", "building", "sub"]
    },
    {
        "id": "8dbb44892dd69cb46b82843d0b1403eeb1116f31",
        "filename": "8dbb44892dd69cb46b82843d0b1403eeb1116f31.jpeg",
        "name": "SUB and AQ Bridge Connection",
        "difficulty": 1,
        "hint": "West of the AQ best east of the SUB.",
        "coordinates": { "lat": 49.27837116626183, "lng": -122.91787147521974 },
        "keywords": ["outside", "dark"]
    },
    {
        "id": "fefde5a6b6d3f60b17f256a2ca14f29e63447b38",
        "filename": "fefde5a6b6d3f60b17f256a2ca14f29e63447b38.jpeg",
        "name": "Long Stairs",
        "difficulty": 4,
        "hint": "Around a science wing.",
        "coordinates": {
            "lat": 49.277191765582515,
            "lng": -122.91630774736406
        },
        "keywords": ["inside", "light", "stairs"]
    },
    {
        "id": "0c95d9f696c017d4543961a66cccd782237c97ee",
        "filename": "0c95d9f696c017d4543961a66cccd782237c97ee.jpeg",
        "name": "Invisible Building (It Is Camouflaged)",
        "difficulty": 5,
        "hint": "Next to the South Science Building.",
        "coordinates": {
            "lat": 49.277184766087764,
            "lng": -122.91896849870685
        },
        "keywords": ["outside", "light", "building"]
    },
    {
        "id": "99acbf949614440ba29c058d75bd726705870ae7",
        "filename": "99acbf949614440ba29c058d75bd726705870ae7.jpeg",
        "name": "Mini Inside Garden",
        "difficulty": 3,
        "hint": "In the AQ.",
        "coordinates": {
            "lat": 49.278273175588275,
            "lng": -122.91597515344621
        },
        "keywords": ["inside", "light", "plants", "garden", "building", "aq"]
    },
    {
        "id": "eaed7ec7ea790b459ff8cd7cc4eecd3deb3d015f",
        "filename": "eaed7ec7ea790b459ff8cd7cc4eecd3deb3d015f.jpeg",
        "name": "SSC Biology Entrance",
        "difficulty": 3,
        "hint": "Attached to the AQ.",
        "coordinates": { "lat": 49.27835366794154, "lng": -122.91677445173265 },
        "keywords": ["inside", "light", "biology"]
    },
    {
        "id": "220a7ff9a225c1592fb0a98dce4bdb141721a611",
        "filename": "220a7ff9a225c1592fb0a98dce4bdb141721a611.jpeg",
        "name": "SSC Physics Entrance",
        "difficulty": 3,
        "hint": "Attached to the AQ.",
        "coordinates": { "lat": 49.27809119239228, "lng": -122.91598588228227 },
        "keywords": ["inside", "light", "physics"]
    },
    {
        "id": "17e6c232aa2a365b5c7cad5d075107a7425a134d",
        "filename": "17e6c232aa2a365b5c7cad5d075107a7425a134d.jpeg",
        "name": "IT Service Centre",
        "difficulty": 3,
        "hint": "At a corner of the AQ.",
        "coordinates": { "lat": 49.27809119239228, "lng": -122.91598588228227 },
        "keywords": ["inside", "light", "building", "aq"]
    },
    {
        "id": "8ff4fb97762e6b1dfedd33a36ed218dbadd25781",
        "filename": "8ff4fb97762e6b1dfedd33a36ed218dbadd25781.jpeg",
        "name": "East Hallway at AQ South-East",
        "difficulty": 2,
        "hint": "At a corner of the AQ.",
        "coordinates": { "lat": 49.27809119239228, "lng": -122.91598588228227 },
        "keywords": ["inside", "light", "building", "aq"]
    },
    {
        "id": "812d9ad7e66af1730c42afccbd58d3d82ee8d94e",
        "filename": "812d9ad7e66af1730c42afccbd58d3d82ee8d94e.jpeg",
        "name": "Art and Seats",
        "difficulty": 5,
        "hint": "In the sciences area.",
        "coordinates": { "lat": 49.27781121693343, "lng": -122.91653841733934 },
        "keywords": ["inside", "light", "building", "art", "sciences"]
    },
    {
        "id": "984e88a8fe871ba563799d2a8e0d7509c64ed04e",
        "filename": "984e88a8fe871ba563799d2a8e0d7509c64ed04e.jpeg",
        "name": "East AQ Hallway",
        "difficulty": 2,
        "hint": "A hallway of the AQ.",
        "coordinates": { "lat": 49.27846740691241, "lng": -122.91586250066759 },
        "keywords": ["inside", "light", "building", "aq", "hallway"]
    },
    {
        "id": "014ef6811087abac5f8ab03521c633b1499d2460",
        "filename": "014ef6811087abac5f8ab03521c633b1499d2460.jpeg",
        "name": "AQ South-East Stairs Entrance",
        "difficulty": 3,
        "hint": "At an entrance to the AQ.",
        "coordinates": {
            "lat": 49.278227679852215,
            "lng": -122.91580349206927
        },
        "keywords": ["outside", "light", "stairs", "building", "aq"]
    },
    {
        "id": "d0660a63a1562b0188b6fba09ee536a625c17247",
        "filename": "d0660a63a1562b0188b6fba09ee536a625c17247.jpeg",
        "name": "SFU Trottier Observatory",
        "difficulty": 2,
        "hint": "East of the AQ.",
        "coordinates": {
            "lat": 49.278462157427214,
            "lng": -122.91520804166795
        },
        "keywords": [
            "outside",
            "light",
            "building",
            "trottier-observatory",
            "attraction"
        ]
    },
    {
        "id": "153efefc7d8078af09f8eaf290f2c8caf590a47a",
        "filename": "153efefc7d8078af09f8eaf290f2c8caf590a47a.jpeg",
        "name": "SFU Trottier Observatory Calendar",
        "difficulty": 4,
        "hint": "At an observatory.",
        "coordinates": { "lat": 49.27845515811276, "lng": -122.91518658399583 },
        "keywords": ["outside", "light", "building", "trottier-observatory"]
    },
    {
        "id": "412fafe65dcaf3f88213ecfe2db0c2bc058d25cb",
        "filename": "412fafe65dcaf3f88213ecfe2db0c2bc058d25cb.jpeg",
        "name": "SFU Trottier Observatory",
        "difficulty": 2,
        "hint": "Good for looking at stars.",
        "coordinates": {
            "lat": 49.278556648075146,
            "lng": -122.91510075330736
        },
        "keywords": [
            "outside",
            "light",
            "building",
            "trottier-observatory",
            "attraction"
        ]
    },
    {
        "id": "f49b4b21380b0011c433610d36d06b0358b3d795",
        "filename": "f49b4b21380b0011c433610d36d06b0358b3d795.jpeg",
        "name": "AQ View from the SFU Trottier Observatory",
        "difficulty": 2,
        "hint": "Near a good place to look at stars. Oh, and there's the AQ by the way.",
        "coordinates": { "lat": 49.2785496487741, "lng": -122.91502565145494 },
        "keywords": [
            "outside",
            "sunset",
            "building",
            "trottier-observatory",
            "aq"
        ]
    },
    {
        "id": "5d041e1018f7d04ab35ad0a71ef50a95ae4786b9",
        "filename": "5d041e1018f7d04ab35ad0a71ef50a95ae4786b9.jpeg",
        "name": "Oval Reflections",
        "difficulty": 1,
        "hint": "Do you really need a hint?",
        "coordinates": { "lat": 49.27899410241936, "lng": -122.91655987501146 },
        "keywords": [
            "outside",
            "light",
            "plants",
            "garden",
            "oval-reflections",
            "attraction",
            "sculpture"
        ]
    },
    {
        "id": "73c099b1d855f6d269bbc2d086870a8013a21dd5",
        "filename": "73c099b1d855f6d269bbc2d086870a8013a21dd5.jpeg",
        "name": "Rotunda Shadow",
        "difficulty": 2,
        "hint": "Above a main bus area.",
        "coordinates": {
            "lat": 49.279620530283694,
            "lng": -122.92017549276355
        },
        "keywords": ["outside", "light", "sun", "building", "rotunda"]
    },
    {
        "id": "f0989b78db339ad57bd5aa9d440f812d132c615e",
        "filename": "f0989b78db339ad57bd5aa9d440f812d132c615e.jpeg",
        "name": "Sun Rotunda",
        "difficulty": 2,
        "hint": "Above where lots of buses go.",
        "coordinates": {
            "lat": 49.279613531133634,
            "lng": -122.92015403509143
        },
        "keywords": ["outside", "light", "sun", "building", "rotunda"]
    },
    {
        "id": "5dea14be156acd566a9ac470ed72beb817f8a879",
        "filename": "5dea14be156acd566a9ac470ed72beb817f8a879.jpeg",
        "name": "Convocation Mall Fountain",
        "difficulty": 1,
        "hint": "At Convocation Mall.",
        "coordinates": { "lat": 49.2793790590326, "lng": -122.91941910982133 },
        "keywords": ["outside", "light", "building", "convocation-mall"]
    },
    {
        "id": "9bcfe94f84ded66ab037b1ecc0143ea6d7f3d819",
        "filename": "9bcfe94f84ded66ab037b1ecc0143ea6d7f3d819.jpeg",
        "name": "Transportation Centre White Piano",
        "difficulty": 1,
        "hint": "At a major bus area.",
        "coordinates": { "lat": 49.27956103747651, "lng": -122.9206529259682 },
        "keywords": [
            "outside",
            "light",
            "building",
            "transportation-centre",
            "piano"
        ]
    },
    {
        "id": "3b5f273ae18c58bc9f93ed806a59d0ea2fd3dcfc",
        "filename": "3b5f273ae18c58bc9f93ed806a59d0ea2fd3dcfc.jpeg",
        "name": "View Area near the SUB",
        "difficulty": 5,
        "hint": "Near the SUB.",
        "coordinates": { "lat": 49.27864763889833, "lng": -122.91886121034624 },
        "keywords": ["outside", "light", "sun", "view", "building"]
    },
    {
        "id": "a6f67b52b126634790a02858ae9506c0337228d2",
        "filename": "a6f67b52b126634790a02858ae9506c0337228d2.jpeg",
        "name": "SUB North View",
        "difficulty": 2,
        "hint": "West of the AQ but east of Convocation Mall.",
        "coordinates": { "lat": 49.27884361856274, "lng": -122.91825503110887 },
        "keywords": ["inside", "light", "building", "sub"]
    },
    {
        "id": "07948f54db5066ef3ed645f19b5759c0472596dd",
        "filename": "07948f54db5066ef3ed645f19b5759c0472596dd.jpeg",
        "name": "Rotunda Middle Level",
        "difficulty": 2,
        "hint": "Next to WMC.",
        "coordinates": { "lat": 49.27935806147661, "lng": -122.92033642530443 },
        "keywords": ["inside", "light", "building", "rotunda"]
    },
    {
        "id": "07b0c9e79cad48d630ecc4fd1be342ec15e65a3b",
        "filename": "07b0c9e79cad48d630ecc4fd1be342ec15e65a3b.jpeg",
        "name": "Inside WMC Looking East",
        "difficulty": 2,
        "hint": "In WMC.",
        "coordinates": { "lat": 49.27988124791579, "lng": -122.92263239622119 },
        "keywords": ["inside", "light", "building", "wmc"]
    },
    {
        "id": "de2124d66e69ce3487475bd438e9a7128df5c1d8",
        "filename": "de2124d66e69ce3487475bd438e9a7128df5c1d8.jpeg",
        "name": "WMC Labatt Sport Court",
        "difficulty": 3,
        "hint": "Somewhere at WMC.",
        "coordinates": {
            "lat": 49.279620530283694,
            "lng": -122.92183846235277
        },
        "keywords": ["outside", "light", "building", "wmc"]
    },
    {
        "id": "1bf29d4394fd49abfc6450e8344a46310837af6c",
        "filename": "1bf29d4394fd49abfc6450e8344a46310837af6c.jpeg",
        "name": "Above WMC",
        "difficulty": 4,
        "hint": "West of the Transportation Centre.",
        "coordinates": {
            "lat": 49.279921492796625,
            "lng": -122.92221933603288
        },
        "keywords": ["outside", "light", "building", "wmc"]
    },
    {
        "id": "346e5bc4af284caf83e48b84cfc4d3fc0b2b1857",
        "filename": "346e5bc4af284caf83e48b84cfc4d3fc0b2b1857.jpeg",
        "name": "Oval Reflections Plaque",
        "difficulty": 5,
        "hint": "At the most famous SFU sculpture.",
        "coordinates": { "lat": 49.27900460127594, "lng": -122.91655451059344 },
        "keywords": [
            "outside",
            "light",
            "plants",
            "garden",
            "oval-reflections",
            "attraction",
            "sculpture"
        ]
    },
    {
        "id": "d33124c59c4c74305280ff213effe3078f69cf6d",
        "filename": "d33124c59c4c74305280ff213effe3078f69cf6d.jpeg",
        "name": "Side of Oval Reflections",
        "difficulty": 1,
        "hint": "Do you really need a hint?",
        "coordinates": { "lat": 49.27902209936528, "lng": -122.9165652394295 },
        "keywords": [
            "outside",
            "light",
            "plants",
            "garden",
            "oval-reflections",
            "attraction",
            "sculpture"
        ]
    },
    {
        "id": "bdd975412df38473be7657e7e03687b4f37eac3f",
        "filename": "bdd975412df38473be7657e7e03687b4f37eac3f.jpeg",
        "name": "WMC Hallway Looking West",
        "difficulty": 2,
        "hint": "In a mall centre that is west.",
        "coordinates": { "lat": 49.279802507836614, "lng": -122.9212322831154 },
        "keywords": ["inside", "light", "building", "wmc", "hallway"]
    },
    {
        "id": "db80a5b2fa90ac2eb29172fb3fd6d3b95b524079",
        "filename": "db80a5b2fa90ac2eb29172fb3fd6d3b95b524079.jpeg",
        "name": "Residence Path Looking West",
        "difficulty": 3,
        "hint": "Lots of students stay here.",
        "coordinates": {
            "lat": 49.280096470157496,
            "lng": -122.92725384235384
        },
        "keywords": ["outside", "light", "building", "residence"]
    },
    {
        "id": "bfc257b158c1d8e15cc969b9c7e8ce674c45661d",
        "filename": "bfc257b158c1d8e15cc969b9c7e8ce674c45661d.jpeg",
        "name": "Looking Over SFU Information Office",
        "difficulty": 2,
        "hint": "Lots of buses go by here.",
        "coordinates": {
            "lat": 49.279347562695264,
            "lng": -122.92033374309541
        },
        "keywords": [
            "outside",
            "light",
            "sun",
            "building",
            "information-office",
            "road"
        ]
    },
    {
        "id": "08b326960ad5575d7cf4efcd9d83e9d00cc377c0",
        "filename": "08b326960ad5575d7cf4efcd9d83e9d00cc377c0.jpeg",
        "name": "Looking at the Library from the Rotunda",
        "difficulty": 1,
        "hint": "Above a bus area.",
        "coordinates": { "lat": 49.27955753789738, "lng": -122.92008161544801 },
        "keywords": ["outside", "light", "building", "library", "rotunda"]
    },
    {
        "id": "354217bce94448109f6cf413f800f42ed4083161",
        "filename": "354217bce94448109f6cf413f800f42ed4083161.jpeg",
        "name": "SUB Entrance",
        "difficulty": 1,
        "hint": "Nea Convocation Mall.",
        "coordinates": { "lat": 49.27915508464133, "lng": -122.91801095008852 },
        "keywords": ["outside", "light", "building", "sub"]
    },
    {
        "id": "5a647ab1ab1fc5845731a99928e7f9b0dcc4c815",
        "filename": "5a647ab1ab1fc5845731a99928e7f9b0dcc4c815.jpeg",
        "name": "AQ Grass Pyramid",
        "difficulty": 1,
        "hint": "In the AQ.",
        "coordinates": { "lat": 49.27892935942105, "lng": -122.91651427745819 },
        "keywords": [
            "outside",
            "light",
            "plants",
            "garden",
            "attraction",
            "building",
            "aq"
        ]
    },
    {
        "id": "1bc4da5e6a028a1bfa113a73528c5ad1a5d26ae4",
        "filename": "1bc4da5e6a028a1bfa113a73528c5ad1a5d26ae4.jpeg",
        "name": "Mackenzie Café",
        "difficulty": 4,
        "hint": "In the AQ.",
        "coordinates": {
            "lat": 49.278922360172906,
            "lng": -122.91562378406526
        },
        "keywords": [
            "inside",
            "light",
            "building",
            "aq",
            "food",
            "mackenzie-cafe"
        ]
    },
    {
        "id": "e9a01de3e4a8b0ea8ca008fb349dabc856e164f6",
        "filename": "e9a01de3e4a8b0ea8ca008fb349dabc856e164f6.jpeg",
        "name": "Patterns",
        "difficulty": 5,
        "hint": "Outside a museum.",
        "coordinates": { "lat": 49.27946654875289, "lng": -122.91511416435243 },
        "keywords": ["inside", "light", "building", "aq", "attraction", "art"]
    },
    {
        "id": "79d080767defaa4fd87ca61773c89c5bc34f4a01",
        "filename": "79d080767defaa4fd87ca61773c89c5bc34f4a01.jpeg",
        "name": "Stairs Down to AQ",
        "difficulty": 3,
        "hint": "Goes to the AQ.",
        "coordinates": {
            "lat": 49.279296818553966,
            "lng": -122.91491568088533
        },
        "keywords": ["inside", "light", "building", "aq", "stairs"]
    },
    {
        "id": "94f2df1c35374481de2acb86e3ae1b890bc388e0",
        "filename": "94f2df1c35374481de2acb86e3ae1b890bc388e0.jpeg",
        "name": "Outside the Museum of Archaeology and Ethnology",
        "difficulty": 3,
        "hint": "Near the AQ.",
        "coordinates": { "lat": 49.27930381774898, "lng": -122.91493713855745 },
        "keywords": [
            "inside",
            "light",
            "building",
            "aq",
            "museum",
            "art",
            "attraction"
        ]
    },
    {
        "id": "60f1451b7e16ba7757ba9c0d5ea3af1638cfcfef",
        "filename": "60f1451b7e16ba7757ba9c0d5ea3af1638cfcfef.jpeg",
        "name": "WMC Floors",
        "difficulty": 4,
        "hint": "In WMC.",
        "coordinates": { "lat": 49.27988649724995, "lng": -122.92254388332368 },
        "keywords": ["inside", "light", "building", "wmc"]
    },
    {
        "id": "8739b03306f4751d3a5bdbc11562060734d29d13",
        "filename": "8739b03306f4751d3a5bdbc11562060734d29d13.jpeg",
        "name": "Path to WMC",
        "difficulty": 2,
        "hint": "Goes to WMC.",
        "coordinates": {
            "lat": 49.279879498137625,
            "lng": -122.92383134365083
        },
        "keywords": ["outside", "light"]
    },
    {
        "id": "95254abff3532d3fdbdd61af18fac97e08c90a70",
        "filename": "95254abff3532d3fdbdd61af18fac97e08c90a70.jpeg",
        "name": "North View in Front of the SUB",
        "difficulty": 2,
        "hint": "The big building is the library.",
        "coordinates": { "lat": 49.27915858424903, "lng": -122.91800558567049 },
        "keywords": ["outside", "light", "building", "library"]
    },
    {
        "id": "56baa0dffc0554aa29be58a481f4fa52a2f06faa",
        "filename": "56baa0dffc0554aa29be58a481f4fa52a2f06faa.jpeg",
        "name": "Eating Area in WMC",
        "difficulty": 3,
        "hint": "In WMC.",
        "coordinates": { "lat": 49.28000548200732, "lng": -122.92170703411104 },
        "keywords": ["inside", "light", "building", "wmc"]
    },
    {
        "id": "65a1bfb0b04679e0ac2efaa4fbc519b1a2774aa0",
        "filename": "65a1bfb0b04679e0ac2efaa4fbc519b1a2774aa0.jpeg",
        "name": "View from WMC",
        "difficulty": 3,
        "hint": "A view from WMC.",
        "coordinates": {
            "lat": 49.280061474734985,
            "lng": -122.92170703411104
        },
        "keywords": ["outside", "light", "building", "wmc", "view"]
    },
    {
        "id": "baeebdb72873f47355be098c96df2bbb8332d4ac",
        "filename": "baeebdb72873f47355be098c96df2bbb8332d4ac.jpeg",
        "name": "Looking East in WMC",
        "difficulty": 2,
        "hint": "In WMC.",
        "coordinates": { "lat": 49.27991496730485, "lng": -122.9222546188662 },
        "keywords": ["inside", "light", "building", "wmc"]
    },
    {
        "id": "1dab4eab08d409890bfabb4032e2e6951805799a",
        "filename": "1dab4eab08d409890bfabb4032e2e6951805799a.jpeg",
        "name": "North View from the Rotunda",
        "difficulty": 4,
        "hint": "Above where lots of buses go.",
        "coordinates": { "lat": 49.27960828177044, "lng": -122.9202425479889 },
        "keywords": ["outside", "light", "building", "rotunda", "view"]
    },
    {
        "id": "782fd69c541761bda97a92d4fd55e09cb15c6435",
        "filename": "782fd69c541761bda97a92d4fd55e09cb15c6435.jpeg",
        "name": "Up the Stairs West from the SFU Transportation Centre",
        "difficulty": 3,
        "hint": "Up the stairs from a piano.",
        "coordinates": { "lat": 49.27955753789738, "lng": -122.92055904865266 },
        "keywords": [
            "outside",
            "light",
            "building",
            "wmc",
            "stairs",
            "transportation-centre"
        ]
    },
    {
        "id": "cf061f3c3943ad509597dd0976a50511829e817c",
        "filename": "cf061f3c3943ad509597dd0976a50511829e817c.jpeg",
        "name": "Parking Lot near Residence",
        "difficulty": 3,
        "hint": "Near residence.",
        "coordinates": { "lat": 49.28062139851518, "lng": -122.92698025703432 },
        "keywords": ["outside", "light", "building", "residence", "parking-lot"]
    },
    {
        "id": "1fce21e574a8c3e8bcb326f6b2d8007e01887575",
        "filename": "1fce21e574a8c3e8bcb326f6b2d8007e01887575.jpeg",
        "name": "SFU Childcare Society",
        "difficulty": 3,
        "hint": "Near SFU residence.",
        "coordinates": { "lat": 49.28028544500992, "lng": -122.92420685291292 },
        "keywords": ["outside", "light", "building", "childcare-society"]
    },
    {
        "id": "415f92763dbe2bcd35e4d32e2612f6b66c8b8a56",
        "filename": "415f92763dbe2bcd35e4d32e2612f6b66c8b8a56.jpeg",
        "name": "Stairs at WMC Labatt Sport Court",
        "difficulty": 2,
        "hint": "Outside WMC.",
        "coordinates": {
            "lat": 49.279613531133634,
            "lng": -122.92181432247163
        },
        "keywords": ["outside", "light", "building", "wmc", "stairs"]
    },
    {
        "id": "242402df08a12f920e7cd3f00ab8f83d98b99f78",
        "filename": "242402df08a12f920e7cd3f00ab8f83d98b99f78.jpeg",
        "name": "Parking Lot West of WMC",
        "difficulty": 3,
        "hint": "Next to WMC.",
        "coordinates": { "lat": 49.28002620499951, "lng": -122.92275943973426 },
        "keywords": ["outside", "light", "building", "wmc", "parking-lot"]
    },
    {
        "id": "d36dc1b769740af6b04ebd55142a27f371f1ec0c",
        "filename": "d36dc1b769740af6b04ebd55142a27f371f1ec0c.jpeg",
        "name": "Middle Stairs of WMC",
        "difficulty": 3,
        "hint": "In WMC.",
        "coordinates": { "lat": 49.27988299769393, "lng": -122.92189478874208 },
        "keywords": ["inside", "light", "building", "wmc", "stairs"]
    },
    {
        "id": "ef871bc4abb4c644b1611ff5870e167133c1a7ad",
        "filename": "ef871bc4abb4c644b1611ff5870e167133c1a7ad.jpeg",
        "name": "South End of the AQ",
        "difficulty": 2,
        "hint": "Looking towards the SUB.",
        "coordinates": { "lat": 49.27850415329309, "lng": -122.9169648885727 },
        "keywords": [
            "outside",
            "light",
            "building",
            "aq",
            "sub",
            "plants",
            "garden"
        ]
    },
    {
        "id": "6695ebc5e16aeed0e33103a3f755af0051385019",
        "filename": "6695ebc5e16aeed0e33103a3f755af0051385019.jpeg",
        "name": "Colored AQ Benches",
        "difficulty": 4,
        "hint": "At the AQ.",
        "coordinates": { "lat": 49.27953129104601, "lng": -122.91702389717103 },
        "keywords": ["outside", "light", "building", "aq", "view"]
    },
    {
        "id": "3e5562087e2422386c873048ca39c8ae41078358",
        "filename": "3e5562087e2422386c873048ca39c8ae41078358.jpeg",
        "name": "Floor Distance Measurements",
        "difficulty": 3,
        "hint": "At a place which is good for looking at stars.",
        "coordinates": { "lat": 49.27855314842475, "lng": -122.91503369808198 },
        "keywords": [
            "outside",
            "light",
            "building",
            "trottier-observatory",
            "aq",
            "attraction"
        ]
    },
    {
        "id": "36c5e8c132ce37b5834ecac1a75c965bde06b2ad",
        "filename": "36c5e8c132ce37b5834ecac1a75c965bde06b2ad.jpeg",
        "name": "Terry Fox Statue",
        "difficulty": 1,
        "hint": "In the AQ.",
        "coordinates": { "lat": 49.27889611298348, "lng": -122.91598320007324 },
        "keywords": [
            "outside",
            "light",
            "plants",
            "garden",
            "attraction",
            "building",
            "aq",
            "sculpture",
            "art"
        ]
    }
]
